waldur_ansible/__init__.py
waldur_ansible/common/__init__.py
waldur_ansible/common/apps.py
waldur_ansible/common/backend.py
waldur_ansible/common/cache_utils.py
waldur_ansible/common/exceptions.py
waldur_ansible/common/extension.py
waldur_ansible/common/filters.py
waldur_ansible/common/managers.py
waldur_ansible/common/models.py
waldur_ansible/common/serializers.py
waldur_ansible/common/urls.py
waldur_ansible/common/utils.py
waldur_ansible/common/views.py
waldur_ansible/common/tests/__init__.py
waldur_ansible/common/tests/integration/__init__.py
waldur_ansible/common/tests/integration/container.py
waldur_ansible/common/tests/integration/image.py
waldur_ansible/common/tests/integration/integration_tests_config.py
waldur_ansible/common/tests/integration/ubuntu1604_container.py
waldur_ansible/common/tests/integration/ubuntu1604_image.py
waldur_ansible/jupyter_hub_management/__init__.py
waldur_ansible/jupyter_hub_management/admin.py
waldur_ansible/jupyter_hub_management/apps.py
waldur_ansible/jupyter_hub_management/constants.py
waldur_ansible/jupyter_hub_management/executors.py
waldur_ansible/jupyter_hub_management/extension.py
waldur_ansible/jupyter_hub_management/jupyter_hub_management_service.py
waldur_ansible/jupyter_hub_management/models.py
waldur_ansible/jupyter_hub_management/serializers.py
waldur_ansible/jupyter_hub_management/urls.py
waldur_ansible/jupyter_hub_management/views.py
waldur_ansible/jupyter_hub_management/backend/__init__.py
waldur_ansible/jupyter_hub_management/backend/additional_extra_args_builders.py
waldur_ansible/jupyter_hub_management/backend/backend.py
waldur_ansible/jupyter_hub_management/backend/error_handlers.py
waldur_ansible/jupyter_hub_management/backend/extracted_information_handlers.py
waldur_ansible/jupyter_hub_management/backend/locking_service.py
waldur_ansible/jupyter_hub_management/migrations/0001_initial.py
waldur_ansible-0.6.2.dist-info/METADATA
waldur_ansible-0.6.2.dist-info/RECORD
waldur_ansible-0.6.2.dist-info/WHEEL
waldur_ansible-0.6.2.dist-info/entry_points.txt
waldur_ansible-0.6.2.dist-info/top_level.txt
