Metadata-Version: 2.1
Name: waldur-ansible
Version: 0.6.2
Summary: Waldur plugin for Ansible playbooks management and execution.
Home-page: https://waldur.com
Author: OpenNode Team
Author-email: info@opennodecloud.com
License: UNKNOWN
Platform: UNKNOWN
Classifier: Framework :: Django
Classifier: Intended Audience :: Developers
Classifier: Intended Audience :: System Administrators
Classifier: Operating System :: OS Independent
Classifier: License :: OSI Approved :: MIT License
Provides-Extra: tests
Requires-Dist: waldur-core (>=0.161.4)
Requires-Dist: waldur-openstack (>=0.43.4)
Requires-Dist: passlib (>=1.7.0)
Provides-Extra: tests
Requires-Dist: ddt (>=1.0.0); extra == 'tests'
Requires-Dist: factory-boy (==2.4.1); extra == 'tests'
Requires-Dist: mock (>=1.0.1); extra == 'tests'
Requires-Dist: docker (==3.2.1); extra == 'tests'
